lib_py_parse/__api__.py
lib_py_parse/__init__.py
lib_py_parse/helper/__init__.py
lib_py_parse/helper/eval_helper.py
lib_py_parse/helper/eval_service.py
lib_py_parse/helper/type_resolver.py
lib_py_parse/parse/__init__.py
lib_py_parse/parse/parse_L0_skeleton.py
lib_py_parse/parse/parse_skeleton.py
lib_py_parse/parse/parser.py
lib_py_parse/parse/rm_comments.py
lib_py_parse/utils/__init__.py
lib_py_parse/utils/constants.py
lib_py_parse/utils/exceptions.py
lib_py_parse/utils/fmt_utils.py
lib_py_parse/utils/fs_mod.py
lib_py_parse/utils/graph_alg.py
lib_py_parse/utils/parsing_utils.py
lib_py_parse-0.0.1.dist-info/METADATA
lib_py_parse-0.0.1.dist-info/WHEEL
lib_py_parse-0.0.1.dist-info/top_level.txt
lib_py_parse-0.0.1.dist-info/RECORD
