Metadata-Version: 2.1
Name: lib-py-parse
Version: 0.0.1
Home-page: http://pypi.python.org/pypi/lib_py_parse/0.0.1
Author: hypothesisbase
Author-email: support@hypothesisbase.com
License: MIT
Requires-Dist: requests
